BeeKeeperRuntimeSDK/__init__.py
BeeKeeperRuntimeSDK/api_client.py
BeeKeeperRuntimeSDK/api_response.py
BeeKeeperRuntimeSDK/configuration.py
BeeKeeperRuntimeSDK/exceptions.py
BeeKeeperRuntimeSDK/py.typed
BeeKeeperRuntimeSDK/rest.py
BeeKeeperRuntimeSDK/api/__init__.py
BeeKeeperRuntimeSDK/api/data_api.py
BeeKeeperRuntimeSDK/api/escrow_api.py
BeeKeeperRuntimeSDK/api/mlflow_api.py
BeeKeeperRuntimeSDK/api/report_api.py
BeeKeeperRuntimeSDK/api/run_api.py
BeeKeeperRuntimeSDK/models/__init__.py
BeeKeeperRuntimeSDK/models/algorithm_status.py
BeeKeeperRuntimeSDK/models/api_v1_data_files_get200_response.py
BeeKeeperRuntimeSDK/models/api_v1_report_post200_response.py
BeeKeeperRuntimeSDK/models/file.py
BeeKeeperRuntimeSDK/models/ping_attestation_status.py
BeeKeeperRuntimeSDK/models/ping_enclave_status.py
BeeKeeperRuntimeSDK/models/ping_escrow_status.py
BeeKeeperRuntimeSDK/models/ping_key_manager_status.py
BeeKeeperRuntimeSDK/models/report.py
BeeKeeperRuntimeSDK/models/sql_query.py
BeeKeeperRuntimeSDK/models/sql_response.py
BeeKeeperRuntimeSDK/models/validation_result.py
BeeKeeperRuntimeSDK-1.5.1.dist-info/METADATA
BeeKeeperRuntimeSDK-1.5.1.dist-info/WHEEL
BeeKeeperRuntimeSDK-1.5.1.dist-info/top_level.txt
BeeKeeperRuntimeSDK-1.5.1.dist-info/RECORD
